teleagent/__init__.py
teleagent/agent/__init__.py
teleagent/agent/agent.py
teleagent/agent/auth.py
teleagent/agent/base.py
teleagent/constants/__init__.py
teleagent/types/__init__.py
teleagent/types/app.py
teleagent/types/proxy.py
teleagent/utils/__init__.py
teleagent/utils/serialization.py
teleagent-0.2.5.dist-info/METADATA
teleagent-0.2.5.dist-info/WHEEL
teleagent-0.2.5.dist-info/top_level.txt
teleagent-0.2.5.dist-info/RECORD
