Metadata-Version: 2.1
Name: teleagent
Version: 0.2.5
Summary: Add your description here
Requires-Python: >=3.12
Requires-Dist: telethon>=1.38.1
